{"#N/A":{"route_id":"","agency_id":"#N/A","trip_id":"#N/A","trip_origin":"#N/A","origin_departure_time":"#N/A","trip_headsign":"#N/A","destination_arrival_time":"#N/A","trip_short_name":"EN 1153","direction_id":1,"version":"","countries":"#N/A","is_active":"#N/A","irregularities":"2026 timetable announced in March","service_id":"2025/05/07-2025/10/05: Wed, Fri, Sun","classes":"#N/A","connections":"","catering":0,"plugs":1,"wheelchair_accessible":"","bikes_allowed":"","car_transport":1,"duration":"#N/A","distance":"#N/A","emissions_co2e":"#N/A","co2_per_km":"#N/A","via":"non-stop","":"#N/A","Merged Doc ID - ONTD_Chatbase_Export":"18h7h10YFhTe1NXj2A1smduQdB9XRGzpN_S7lZN_juBY","Merged Doc URL - ONTD_Chatbase_Export":"https://docs.google.com/document/d/18h7h10YFhTe1NXj2A1smduQdB9XRGzpN_S7lZN_juBY/edit?usp=drivesdk","Link to merged Doc - ONTD_Chatbase_Export":"ONTD_Chatbase_export_05/02/2025_May 2 2025 8:08 PM","Document Merge Status - ONTD_Chatbase_Export":"Data merged and appended successfully; Manually run by jme@wegewerk.com; Timestamp: May 2 2025 4:09 PM"},"BDŽ 2636":{"route_id":142,"agency_id":"BDŽ","trip_id":"BDŽ 2636","trip_origin":"Dobrich","origin_departure_time":"1899-12-30T20:35:00.000Z","trip_headsign":"Sofia","destination_arrival_time":"1899-12-30T05:45:00.000Z","trip_short_name":"2636","direction_id":0,"version":"","countries":"BG","is_active":"Y","irregularities":"Train runs only to Poveljanovo but with 1 sleeper through coach to Sofia, not indicated in the official timetable","service_id":"2026: Daily","classes":"sleeper","connections":"","catering":0,"plugs":1,"wheelchair_accessible":2,"bikes_allowed":2,"car_transport":2,"duration":"1899-12-30T09:10:00.000Z","distance":572,"emissions_co2e":"","co2_per_km":"","via":"Donchevo - Botevo - Oborishte - General Kiselovo - Valchi Dol - Suvorovo - Chernevo - Kipra - Devnya - Poveljanovo - Zverino - Svoge - Kurilo - Sofia Sever","":"#N/A","Merged Doc ID - ONTD_Chatbase_Export":"1GWLuutv4VN3px7uay2iCJEiNza9dApi5k5JUPCHid14","Merged Doc URL - ONTD_Chatbase_Export":"https://docs.google.com/document/d/1GWLuutv4VN3px7uay2iCJEiNza9dApi5k5JUPCHid14/edit?usp=drivesdk","Link to merged Doc - ONTD_Chatbase_Export":"ONTD_Chatbase_export_05/02/2025_May 2 2025 8:03 PM","Document Merge Status - ONTD_Chatbase_Export":"Data merged and appended successfully; Manually run by jme@wegewerk.com; Timestamp: May 2 2025 4:08 PM"},"BDŽ 2637":{"route_id":142,"agency_id":"BDŽ","trip_id":"BDŽ 2637","trip_origin":"Sofia","origin_departure_time":"1899-12-30T23:00:00.000Z","trip_headsign":"Dobrich","destination_arrival_time":"1899-12-30T08:05:00.000Z","trip_short_name":"2637","direction_id":1,"version":"","countries":"BG","is_active":"Y","irregularities":"Train runs only to Poveljanovo but with 1 sleeper through coach to Dobrich, not indicated in the official timetable","service_id":"2026: Daily","classes":"sleeper","connections":"","catering":0,"plugs":1,"wheelchair_accessible":2,"bikes_allowed":2,"car_transport":2,"duration":"1899-12-30T09:05:00.000Z","distance":572,"emissions_co2e":"","co2_per_km":"","via":"Sofia Sever - Rebrovo - Svoge - Cerovo - Bov - Lakatnik - Zverino - Mezdra - Roman - Cherven Bryag - Pleven - Poveljanovo - Devnya - Kipra - Chernevo - Suvorovo - Valchi Dol - General Kiselovo - Oborishte - Botevo - Donchevo","":"#N/A","Merged Doc ID - ONTD_Chatbase_Export":"1GWLuutv4VN3px7uay2iCJEiNza9dApi5k5JUPCHid14","Merged Doc URL - ONTD_Chatbase_Export":"https://docs.google.com/document/d/1GWLuutv4VN3px7uay2iCJEiNza9dApi5k5JUPCHid14/edit?usp=drivesdk","Link to merged Doc - ONTD_Chatbase_Export":"ONTD_Chatbase_export_05/02/2025_May 2 2025 8:03 PM","Document Merge Status - ONTD_Chatbase_Export":"Data merged and appended successfully; Manually run by jme@wegewerk.com; Timestamp: May 2 2025 4:08 PM"},"CFR 1821":{"route_id":21,"agency_id":"CFR","trip_id":"CFR 1821","trip_origin":"București Nord","origin_departure_time":"1899-12-30T23:28:00.000Z","trip_headsign":"Arad","destination_arrival_time":"1899-12-30T11:24:00.000Z","trip_short_name":"1821","direction_id":0,"version":"","countries":"RO","is_active":"Y","irregularities":"","service_id":"Daily","classes":"seat, couchette, sleeper","connections":"","catering":0,"plugs":1,"wheelchair_accessible":"","bikes_allowed":2,"car_transport":2,"duration":"1899-12-30T11:56:00.000Z","distance":604,"emissions_co2e":14,"co2_per_km":23.17880794701987,"via":"Craiova - Petroșani - Deva","":"#N/A","Merged Doc ID - ONTD_Chatbase_Export":"1GWLuutv4VN3px7uay2iCJEiNza9dApi5k5JUPCHid14","Merged Doc URL - ONTD_Chatbase_Export":"https://docs.google.com/document/d/1GWLuutv4VN3px7uay2iCJEiNza9dApi5k5JUPCHid14/edit?usp=drivesdk","Link to merged Doc - ONTD_Chatbase_Export":"ONTD_Chatbase_export_05/02/2025_May 2 2025 8:03 PM","Document Merge Status - ONTD_Chatbase_Export":"Data merged and appended successfully; Manually run by jme@wegewerk.com; Timestamp: May 2 2025 4:08 PM"},"CFR 1822":{"route_id":21,"agency_id":"CFR","trip_id":"CFR 1822","trip_origin":"Arad","origin_departure_time":"1899-12-30T17:48:00.000Z","trip_headsign":"București Nord","destination_arrival_time":"1899-12-30T05:25:00.000Z","trip_short_name":"1822","direction_id":1,"version":"","countries":"RO","is_active":"Y","irregularities":"","service_id":"Daily","classes":"seat, couchette, sleeper","connections":"","catering":0,"plugs":1,"wheelchair_accessible":"","bikes_allowed":2,"car_transport":2,"duration":"1899-12-30T11:37:00.000Z","distance":604,"emissions_co2e":14,"co2_per_km":23.17880794701987,"via":"Deva - Petroșani - Craiova","":"#N/A","Merged Doc ID - ONTD_Chatbase_Export":"1GWLuutv4VN3px7uay2iCJEiNza9dApi5k5JUPCHid14","Merged Doc URL - ONTD_Chatbase_Export":"https://docs.google.com/document/d/1GWLuutv4VN3px7uay2iCJEiNza9dApi5k5JUPCHid14/edit?usp=drivesdk","Link to merged Doc - ONTD_Chatbase_Export":"ONTD_Chatbase_export_05/02/2025_May 2 2025 8:03 PM","Document Merge Status - ONTD_Chatbase_Export":"Data merged and appended successfully; Manually run by jme@wegewerk.com; Timestamp: May 2 2025 4:08 PM"},"CFR 1920":{"route_id":26,"agency_id":"CFR","trip_id":"CFR 1920","trip_origin":"Constanța","origin_departure_time":"1899-12-30T18:43:00.000Z","trip_headsign":"Oradea","destination_arrival_time":"1899-12-30T12:40:00.000Z","trip_short_name":"1920","direction_id":0,"version":"","countries":"RO","is_active":"Y","irregularities":"","service_id":"2026/06/11-09/06: Daily","classes":"seat, couchette, sleeper","connections":"","catering":0,"plugs":"","wheelchair_accessible":"","bikes_allowed":"","car_transport":"","duration":"1899-12-30T17:57:00.000Z","distance":991,"emissions_co2e":"","co2_per_km":"","via":"Medgidia - Fetești - București Nord - Videle - Roșiori Nord - Caracal - Craiova - Petroșani - Subcetate - Simeria - Deva - Ilia - Arad - Chișineu-Criș","":"#N/A","Merged Doc ID - ONTD_Chatbase_Export":"1GWLuutv4VN3px7uay2iCJEiNza9dApi5k5JUPCHid14","Merged Doc URL - ONTD_Chatbase_Export":"https://docs.google.com/document/d/1GWLuutv4VN3px7uay2iCJEiNza9dApi5k5JUPCHid14/edit?usp=drivesdk","Link to merged Doc - ONTD_Chatbase_Export":"ONTD_Chatbase_export_05/02/2025_May 2 2025 8:03 PM","Document Merge Status - ONTD_Chatbase_Export":"Data merged and appended successfully; Manually run by jme@wegewerk.com; Timestamp: May 2 2025 4:08 PM"},"CFR 1922":{"route_id":26,"agency_id":"CFR","trip_id":"CFR 1922","trip_origin":"Oradea","origin_departure_time":"1899-12-30T14:20:00.000Z","trip_headsign":"Constanța","destination_arrival_time":"1899-12-30T08:31:00.000Z","trip_short_name":"1922","direction_id":1,"version":"","countries":"RO","is_active":"Y","irregularities":"","service_id":"2026/06/11-09/06: Daily","classes":"seat, couchette, sleeper","connections":"","catering":0,"plugs":"","wheelchair_accessible":"","bikes_allowed":"","car_transport":"","duration":"1899-12-30T18:11:00.000Z","distance":991,"emissions_co2e":"","co2_per_km":"","via":"Chișineu-Criș - Arad - Ilia - Deva - Simeria - Subcetate - Petroșani - Târgu Jiu - Craiova - Caracal - Roșiori Nord - Videle - București Nord - Fetești - Medgidia","":"#N/A","Merged Doc ID - ONTD_Chatbase_Export":"1GWLuutv4VN3px7uay2iCJEiNza9dApi5k5JUPCHid14","Merged Doc URL - ONTD_Chatbase_Export":"https://docs.google.com/document/d/1GWLuutv4VN3px7uay2iCJEiNza9dApi5k5JUPCHid14/edit?usp=drivesdk","Link to merged Doc - ONTD_Chatbase_Export":"ONTD_Chatbase_export_05/02/2025_May 2 2025 8:03 PM","Document Merge Status - ONTD_Chatbase_Export":"Data merged and appended successfully; Manually run by jme@wegewerk.com; Timestamp: May 2 2025 4:08 PM"},"CFR 1941":{"route_id":25,"agency_id":"CFR","trip_id":"CFR 1941","trip_origin":"Satu Mare","origin_departure_time":"1899-12-30T12:20:00.000Z","trip_headsign":"Mangalia","destination_arrival_time":"1899-12-30T07:30:00.000Z","trip_short_name":"1941","direction_id":0,"version":"","countries":"RO","is_active":"Y","irregularities":"","service_id":"2024/06/14-2024/09/07: Daily","classes":"seat, couchette, sleeper","connections":"","catering":0,"plugs":2,"wheelchair_accessible":"","bikes_allowed":2,"car_transport":2,"duration":"1899-12-30T19:10:00.000Z","distance":974,"emissions_co2e":"","co2_per_km":"","via":"Baia Mare - Dej - Beclean pe Somes - Deda - Gheorgheni - Miercurea Ciuc - Brașov - Constanța","":"#N/A","Merged Doc ID - ONTD_Chatbase_Export":"1GWLuutv4VN3px7uay2iCJEiNza9dApi5k5JUPCHid14","Merged Doc URL - ONTD_Chatbase_Export":"https://docs.google.com/document/d/1GWLuutv4VN3px7uay2iCJEiNza9dApi5k5JUPCHid14/edit?usp=drivesdk","Link to merged Doc - ONTD_Chatbase_Export":"ONTD_Chatbase_export_05/02/2025_May 2 2025 8:03 PM","Document Merge Status - ONTD_Chatbase_Export":"Data merged and appended successfully; Manually run by jme@wegewerk.com; Timestamp: May 2 2025 4:08 PM"},"CFR 1942/R 8810":{"route_id":25,"agency_id":"CFR","trip_id":"CFR 1942/R 8810","trip_origin":"Mangalia","origin_departure_time":"1899-12-30T14:26:00.000Z","trip_headsign":"Satu Mare","destination_arrival_time":"1899-12-30T09:39:00.000Z","trip_short_name":"1942/R 8810","direction_id":1,"version":"","countries":"RO","is_active":"Y","irregularities":"","service_id":"2024/06/15-2024/09/08: Daily","classes":"seat, couchette, sleeper","connections":"","catering":0,"plugs":2,"wheelchair_accessible":2,"bikes_allowed":2,"car_transport":2,"duration":"1899-12-30T19:13:00.000Z","distance":974,"emissions_co2e":"","co2_per_km":"","via":"Constanța - Bucuresti Baneasa - Ploiești Vest - Brașov - Miercurea Ciuc - Gheorgheni - Dej - Baia Mare","":"#N/A","Merged Doc ID - ONTD_Chatbase_Export":"1GWLuutv4VN3px7uay2iCJEiNza9dApi5k5JUPCHid14","Merged Doc URL - ONTD_Chatbase_Export":"https://docs.google.com/document/d/1GWLuutv4VN3px7uay2iCJEiNza9dApi5k5JUPCHid14/edit?usp=drivesdk","Link to merged Doc - ONTD_Chatbase_Export":"ONTD_Chatbase_export_05/02/2025_May 2 2025 8:03 PM","Document Merge Status - ONTD_Chatbase_Export":"Data merged and appended successfully; Manually run by jme@wegewerk.com; Timestamp: May 2 2025 4:08 PM"},"CFR 1952":{"route_id":13,"agency_id":"CFR","trip_id":"CFR 1952","trip_origin":"Suceava Nord","origin_departure_time":"1899-12-30T20:25:00.000Z","trip_headsign":"Constanța","destination_arrival_time":"1899-12-30T03:59:00.000Z","trip_short_name":"1952","direction_id":0,"version":"","countries":"RO","is_active":"Y","irregularities":"","service_id":"2024/06/14-2024/09/07: Daily","classes":"seat, couchette","connections":"","catering":0,"plugs":2,"wheelchair_accessible":2,"bikes_allowed":2,"car_transport":2,"duration":"1899-12-30T07:34:00.000Z","distance":526,"emissions_co2e":12.7,"co2_per_km":24.14448669201521,"via":"Suceava - Bacău - Buzău","":"#N/A","Merged Doc ID - ONTD_Chatbase_Export":"1GWLuutv4VN3px7uay2iCJEiNza9dApi5k5JUPCHid14","Merged Doc URL - ONTD_Chatbase_Export":"https://docs.google.com/document/d/1GWLuutv4VN3px7uay2iCJEiNza9dApi5k5JUPCHid14/edit?usp=drivesdk","Link to merged Doc - ONTD_Chatbase_Export":"ONTD_Chatbase_export_05/02/2025_May 2 2025 8:03 PM","Document Merge Status - ONTD_Chatbase_Export":"Data merged and appended successfully; Manually run by jme@wegewerk.com; Timestamp: May 2 2025 4:08 PM"},"CFR 1954":{"route_id":13,"agency_id":"CFR","trip_id":"CFR 1954","trip_origin":"Constanța","origin_departure_time":"1899-12-30T23:30:00.000Z","trip_headsign":"Suceava Nord","destination_arrival_time":"1899-12-30T07:16:00.000Z","trip_short_name":"1954","direction_id":1,"version":"","countries":"RO","is_active":"Y","irregularities":"","service_id":"2024/06/15-2024/09/08: Daily","classes":"seat, couchette","connections":"","catering":0,"plugs":2,"wheelchair_accessible":2,"bikes_allowed":2,"car_transport":2,"duration":"1899-12-30T07:46:00.000Z","distance":526,"emissions_co2e":12.7,"co2_per_km":24.14448669201521,"via":"Fetești - Buzău - Bacău - Suceava","":"#N/A","Merged Doc ID - ONTD_Chatbase_Export":"1GWLuutv4VN3px7uay2iCJEiNza9dApi5k5JUPCHid14","Merged Doc URL - ONTD_Chatbase_Export":"https://docs.google.com/document/d/1GWLuutv4VN3px7uay2iCJEiNza9dApi5k5JUPCHid14/edit?usp=drivesdk","Link to merged Doc - ONTD_Chatbase_Export":"ONTD_Chatbase_export_05/02/2025_May 2 2025 8:03 PM","Document Merge Status - ONTD_Chatbase_Export":"Data merged and appended successfully; Manually run by jme@wegewerk.com; Timestamp: May 2 2025 4:08 PM"},"FS IC Notte 1959 (S)":{"route_id":104,"agency_id":"FS","trip_id":"FS IC Notte 1959 (S)","trip_origin":"Roma Termini","origin_departure_time":"1899-12-30T23:00:00.000Z","trip_headsign":"Siracusa","destination_arrival_time":"1899-12-30T11:29:00.000Z","trip_short_name":"IC Notte 1959 (S)","direction_id":0,"version":"","countries":"IT","is_active":"Y","irregularities":"","service_id":"Daily","classes":"seat, couchette, sleeper","connections":"","catering":0,"plugs":"","wheelchair_accessible":"","bikes_allowed":"","car_transport":2,"duration":"1899-12-30T12:29:00.000Z","distance":820,"emissions_co2e":16.5,"co2_per_km":20.121951219512194,"via":"Lamezia Terme Centrale - Messina Centrale - Taormina Giardini - Catania Centrale","":"#N/A","Merged Doc ID - ONTD_Chatbase_Export":"1GWLuutv4VN3px7uay2iCJEiNza9dApi5k5JUPCHid14","Merged Doc URL - ONTD_Chatbase_Export":"https://docs.google.com/document/d/1GWLuutv4VN3px7uay2iCJEiNza9dApi5k5JUPCHid14/edit?usp=drivesdk","Link to merged Doc - ONTD_Chatbase_Export":"ONTD_Chatbase_export_05/02/2025_May 2 2025 8:03 PM","Document Merge Status - ONTD_Chatbase_Export":"Data merged and appended successfully; Manually run by jme@wegewerk.com; Timestamp: May 2 2025 4:08 PM"},"FS IC Notte 1960":{"route_id":104,"agency_id":"FS","trip_id":"FS IC Notte 1960","trip_origin":"Siracusa","origin_departure_time":"1899-12-30T21:45:00.000Z","trip_headsign":"Roma Termini","destination_arrival_time":"1899-12-30T09:51:00.000Z","trip_short_name":"IC Notte 1960","direction_id":1,"version":"","countries":"IT","is_active":"Y","irregularities":"","service_id":"Daily","classes":"seat, couchette, sleeper","connections":"","catering":0,"plugs":"","wheelchair_accessible":"","bikes_allowed":"","car_transport":2,"duration":"1899-12-30T12:06:00.000Z","distance":820,"emissions_co2e":16.5,"co2_per_km":20.121951219512194,"via":"Catania Centrale - Taormina Giardini - Messina Centrale - Salerno - Baqël","":"#N/A","Merged Doc ID - ONTD_Chatbase_Export":"1GWLuutv4VN3px7uay2iCJEiNza9dApi5k5JUPCHid14","Merged Doc URL - ONTD_Chatbase_Export":"https://docs.google.com/document/d/1GWLuutv4VN3px7uay2iCJEiNza9dApi5k5JUPCHid14/edit?usp=drivesdk","Link to merged Doc - ONTD_Chatbase_Export":"ONTD_Chatbase_export_05/02/2025_May 2 2025 8:03 PM","Document Merge Status - ONTD_Chatbase_Export":"Data merged and appended successfully; Manually run by jme@wegewerk.com; Timestamp: May 2 2025 4:08 PM"},"FS IC Notte 757":{"route_id":97,"agency_id":"FS","trip_id":"FS IC Notte 757","trip_origin":"Torino Lingotto","origin_departure_time":"1899-12-30T20:58:00.000Z","trip_headsign":"Lecce","destination_arrival_time":"1899-12-30T10:10:00.000Z","trip_short_name":"IC Notte 757","direction_id":1,"version":"","countries":"IT","is_active":"Y","irregularities":"","service_id":"Daily","classes":"seat, couchette, sleeper","connections":"","catering":0,"plugs":"","wheelchair_accessible":"","bikes_allowed":"","car_transport":2,"duration":"1899-12-30T13:12:00.000Z","distance":1147,"emissions_co2e":23,"co2_per_km":20.05231037489102,"via":"Bologna Centrale - Foggia - Bari Centrale - Brindisi","":"#N/A","Merged Doc ID - ONTD_Chatbase_Export":"1GWLuutv4VN3px7uay2iCJEiNza9dApi5k5JUPCHid14","Merged Doc URL - ONTD_Chatbase_Export":"https://docs.google.com/document/d/1GWLuutv4VN3px7uay2iCJEiNza9dApi5k5JUPCHid14/edit?usp=drivesdk","Link to merged Doc - ONTD_Chatbase_Export":"ONTD_Chatbase_export_05/02/2025_May 2 2025 8:03 PM","Document Merge Status - ONTD_Chatbase_Export":"Data merged and appended successfully; Manually run by jme@wegewerk.com; Timestamp: May 2 2025 4:08 PM"},"HŽPP 1840":{"route_id":47,"agency_id":"HŽPP","trip_id":"HŽPP 1840","trip_origin":"Vukovar","origin_departure_time":"1899-12-30T16:57:00.000Z","trip_headsign":"Split","destination_arrival_time":"1899-12-30T06:51:00.000Z","trip_short_name":"1840","direction_id":0,"version":"","countries":"HR","is_active":"Y","irregularities":"","service_id":"Daily (Jul-Aug)","classes":"seat, couchette, sleeper","connections":"","catering":2,"plugs":1,"wheelchair_accessible":2,"bikes_allowed":1,"car_transport":2,"duration":"1899-12-30T13:54:00.000Z","distance":700,"emissions_co2e":6.5,"co2_per_km":9.285714285714286,"via":"Slavonski Brod - Zagreb Gl. K. - Karlovac - Knin","":"#N/A","Merged Doc ID - ONTD_Chatbase_Export":"1GWLuutv4VN3px7uay2iCJEiNza9dApi5k5JUPCHid14","Merged Doc URL - ONTD_Chatbase_Export":"https://docs.google.com/document/d/1GWLuutv4VN3px7uay2iCJEiNza9dApi5k5JUPCHid14/edit?usp=drivesdk","Link to merged Doc - ONTD_Chatbase_Export":"ONTD_Chatbase_export_05/02/2025_May 2 2025 8:03 PM","Document Merge Status - ONTD_Chatbase_Export":"Data merged and appended successfully; Manually run by jme@wegewerk.com; Timestamp: May 2 2025 4:08 PM"},"HŽPP 1841":{"route_id":47,"agency_id":"HŽPP","trip_id":"HŽPP 1841","trip_origin":"Split","origin_departure_time":"1899-12-30T21:11:00.000Z","trip_headsign":"Vukovar","destination_arrival_time":"1899-12-30T11:11:00.000Z","trip_short_name":"1841","direction_id":1,"version":"","countries":"HR","is_active":"Y","irregularities":"","service_id":"Daily (Jul-Aug)","classes":"seat, couchette, sleeper","connections":"","catering":2,"plugs":1,"wheelchair_accessible":2,"bikes_allowed":1,"car_transport":2,"duration":"1899-12-30T14:00:00.000Z","distance":700,"emissions_co2e":6.5,"co2_per_km":9.285714285714286,"via":"Knin - Zagreb Gl. K. - Slavonski Brod","":"#N/A","Merged Doc ID - ONTD_Chatbase_Export":"1GWLuutv4VN3px7uay2iCJEiNza9dApi5k5JUPCHid14","Merged Doc URL - ONTD_Chatbase_Export":"https://docs.google.com/document/d/1GWLuutv4VN3px7uay2iCJEiNza9dApi5k5JUPCHid14/edit?usp=drivesdk","Link to merged Doc - ONTD_Chatbase_Export":"ONTD_Chatbase_export_05/02/2025_May 2 2025 8:03 PM","Document Merge Status - ONTD_Chatbase_Export":"Data merged and appended successfully; Manually run by jme@wegewerk.com; Timestamp: May 2 2025 4:08 PM"},"HŽPP 1880":{"route_id":48,"agency_id":"HŽPP","trip_id":"HŽPP 1880","trip_origin":"Osijek","origin_departure_time":"1899-12-30T19:48:00.000Z","trip_headsign":"Split","destination_arrival_time":"1899-12-30T09:21:00.000Z","trip_short_name":"1880","direction_id":0,"version":"","countries":"HR","is_active":"Y","irregularities":"","service_id":"Daily (Jul-Aug)","classes":"seat, couchette, sleeper","connections":"","catering":2,"plugs":1,"wheelchair_accessible":2,"bikes_allowed":1,"car_transport":2,"duration":"1899-12-30T13:33:00.000Z","distance":677,"emissions_co2e":6.5,"co2_per_km":9.601181683899558,"via":"Zagreb Gl. K. - Knin","":"#N/A","Merged Doc ID - ONTD_Chatbase_Export":"1GWLuutv4VN3px7uay2iCJEiNza9dApi5k5JUPCHid14","Merged Doc URL - ONTD_Chatbase_Export":"https://docs.google.com/document/d/1GWLuutv4VN3px7uay2iCJEiNza9dApi5k5JUPCHid14/edit?usp=drivesdk","Link to merged Doc - ONTD_Chatbase_Export":"ONTD_Chatbase_export_05/02/2025_May 2 2025 8:03 PM","Document Merge Status - ONTD_Chatbase_Export":"Data merged and appended successfully; Manually run by jme@wegewerk.com; Timestamp: May 2 2025 4:08 PM"},"HŽPP 1881":{"route_id":48,"agency_id":"HŽPP","trip_id":"HŽPP 1881","trip_origin":"Split","origin_departure_time":"1899-12-30T22:23:00.000Z","trip_headsign":"Osijek","destination_arrival_time":"1899-12-30T12:04:00.000Z","trip_short_name":"1881","direction_id":1,"version":"","countries":"HR","is_active":"Y","irregularities":"","service_id":"Daily (Jul-Aug)","classes":"seat, couchette, sleeper","connections":"","catering":2,"plugs":1,"wheelchair_accessible":2,"bikes_allowed":1,"car_transport":2,"duration":"1899-12-30T13:41:00.000Z","distance":677,"emissions_co2e":6.5,"co2_per_km":9.601181683899558,"via":"Knin - Zagreb Gl. K. - Bjelovar","":"#N/A","Merged Doc ID - ONTD_Chatbase_Export":"1GWLuutv4VN3px7uay2iCJEiNza9dApi5k5JUPCHid14","Merged Doc URL - ONTD_Chatbase_Export":"https://docs.google.com/document/d/1GWLuutv4VN3px7uay2iCJEiNza9dApi5k5JUPCHid14/edit?usp=drivesdk","Link to merged Doc - ONTD_Chatbase_Export":"ONTD_Chatbase_export_05/02/2025_May 2 2025 8:03 PM","Document Merge Status - ONTD_Chatbase_Export":"Data merged and appended successfully; Manually run by jme@wegewerk.com; Timestamp: May 2 2025 4:08 PM"},"PKP TLK 35190":{"route_id":125,"agency_id":"PKP","trip_id":"PKP TLK 35190","trip_origin":"Kraków Gł.","origin_departure_time":"1899-12-30T20:14:00.000Z","trip_headsign":"Łeba","destination_arrival_time":"1899-12-30T08:13:00.000Z","trip_short_name":"TLK 35190","direction_id":0,"version":"","countries":"PL","is_active":"Y","irregularities":"","service_id":"2026/06/26-2026/08/30: Daily","classes":"seat, sleeper","connections":"","catering":2,"plugs":"","wheelchair_accessible":"","bikes_allowed":"","car_transport":2,"duration":"1899-12-30T11:59:00.000Z","distance":703,"emissions_co2e":24.3,"co2_per_km":34.566145092460886,"via":"Częstochowa - Łódź Kaliska - Toruń Gł. - Gdynia Główna","":"#N/A","Merged Doc ID - ONTD_Chatbase_Export":"1GWLuutv4VN3px7uay2iCJEiNza9dApi5k5JUPCHid14","Merged Doc URL - ONTD_Chatbase_Export":"https://docs.google.com/document/d/1GWLuutv4VN3px7uay2iCJEiNza9dApi5k5JUPCHid14/edit?usp=drivesdk","Link to merged Doc - ONTD_Chatbase_Export":"ONTD_Chatbase_export_05/02/2025_May 2 2025 8:03 PM","Document Merge Status - ONTD_Chatbase_Export":"Data merged and appended successfully; Manually run by jme@wegewerk.com; Timestamp: May 2 2025 4:08 PM"},"PKP TLK 53190":{"route_id":125,"agency_id":"PKP","trip_id":"PKP TLK 53190","trip_origin":"Łeba","origin_departure_time":"1899-12-30T21:00:00.000Z","trip_headsign":"Kraków Gł.","destination_arrival_time":"1899-12-30T08:48:00.000Z","trip_short_name":"TLK 53190","direction_id":1,"version":"","countries":"PL","is_active":"Y","irregularities":"","service_id":"2026/06/27-2026/08/31: Daily","classes":"seat, sleeper","connections":"","catering":2,"plugs":"","wheelchair_accessible":"","bikes_allowed":"","car_transport":2,"duration":"1899-12-30T11:48:00.000Z","distance":703,"emissions_co2e":24.3,"co2_per_km":34.566145092460886,"via":"Gdynia Gł. - Gdańsk Gł. - Tczew - Łódź Kaliska - Częstochowa","":"#N/A","Merged Doc ID - ONTD_Chatbase_Export":"1GWLuutv4VN3px7uay2iCJEiNza9dApi5k5JUPCHid14","Merged Doc URL - ONTD_Chatbase_Export":"https://docs.google.com/document/d/1GWLuutv4VN3px7uay2iCJEiNza9dApi5k5JUPCHid14/edit?usp=drivesdk","Link to merged Doc - ONTD_Chatbase_Export":"ONTD_Chatbase_export_05/02/2025_May 2 2025 8:03 PM","Document Merge Status - ONTD_Chatbase_Export":"Data merged and appended successfully; Manually run by jme@wegewerk.com; Timestamp: May 2 2025 4:08 PM"},"PKP/ČD EC 461":{"route_id":124,"agency_id":"PKP/ČD","trip_id":"PKP/ČD EC 461","trip_origin":"Gdynia Gł.","origin_departure_time":"1899-12-30T21:59:00.000Z","trip_headsign":"Praha hl.n.","destination_arrival_time":"1899-12-30T09:14:00.000Z","trip_short_name":"EC 461","direction_id":1,"version":"","countries":"PL, CZ","is_active":"Y","irregularities":"","service_id":"2026: Daily","classes":"seat, couchette, sleeper","connections":"","catering":3,"plugs":"","wheelchair_accessible":"","bikes_allowed":"","car_transport":2,"duration":"1899-12-30T11:15:00.000Z","distance":856,"emissions_co2e":27.1,"co2_per_km":31.658878504672902,"via":"Gdańsk Gł. - Bydgoszcz Gł. - Wrocław Gł. - Kłodzko Miasto - Międzylesie - Lichkov - Pardubice hl.n.","":"#N/A","Merged Doc ID - ONTD_Chatbase_Export":"1GWLuutv4VN3px7uay2iCJEiNza9dApi5k5JUPCHid14","Merged Doc URL - ONTD_Chatbase_Export":"https://docs.google.com/document/d/1GWLuutv4VN3px7uay2iCJEiNza9dApi5k5JUPCHid14/edit?usp=drivesdk","Link to merged Doc - ONTD_Chatbase_Export":"ONTD_Chatbase_export_05/02/2025_May 2 2025 8:03 PM","Document Merge Status - ONTD_Chatbase_Export":"Data merged and appended successfully; Manually run by jme@wegewerk.com; Timestamp: May 2 2025 4:08 PM"},"PKP/ČD TLK 403/50171":{"route_id":265,"agency_id":"PKP/ČD","trip_id":"PKP/ČD TLK 403/50171","trip_origin":"Bohumín","origin_departure_time":"1899-12-30T19:27:00.000Z","trip_headsign":"Hel","destination_arrival_time":"1899-12-30T07:09:00.000Z","trip_short_name":"TLK 403/50171","direction_id":0,"version":"","countries":"CZ, PL","is_active":"Y","irregularities":"","service_id":"2026/06/26-2026/08/30: Daily","classes":"","connections":"","catering":"","plugs":"","wheelchair_accessible":"","bikes_allowed":"","car_transport":"","duration":"1899-12-30T11:42:00.000Z","distance":"","emissions_co2e":"","co2_per_km":"","via":"non-stop","":"#N/A","Merged Doc ID - ONTD_Chatbase_Export":"","Merged Doc URL - ONTD_Chatbase_Export":"","Link to merged Doc - ONTD_Chatbase_Export":"","Document Merge Status - ONTD_Chatbase_Export":""},"PKP/ČD TLK 55170/402":{"route_id":265,"agency_id":"PKP/ČD","trip_id":"PKP/ČD TLK 55170/402","trip_origin":"Hel","origin_departure_time":"1899-12-30T19:23:00.000Z","trip_headsign":"Bohumín","destination_arrival_time":"1899-12-30T06:54:00.000Z","trip_short_name":"TLK 55170/402","direction_id":1,"version":"","countries":"CZ, PL","is_active":"Y","irregularities":"","service_id":"2026/06/26-2026/08/30: Daily","classes":"","connections":"","catering":"","plugs":"","wheelchair_accessible":"","bikes_allowed":"","car_transport":"","duration":"1899-12-30T11:31:00.000Z","distance":"","emissions_co2e":"","co2_per_km":"","via":"non-stop","":"#N/A","Merged Doc ID - ONTD_Chatbase_Export":"","Merged Doc URL - ONTD_Chatbase_Export":"","Link to merged Doc - ONTD_Chatbase_Export":"","Document Merge Status - ONTD_Chatbase_Export":""},"PKP/ČD TLK 403":{"route_id":266,"agency_id":"PKP/ČD","trip_id":"PKP/ČD TLK 403","trip_origin":"Bohumín","origin_departure_time":"1899-12-30T19:27:00.000Z","trip_headsign":"Łeba","destination_arrival_time":"1899-12-30T07:13:00.000Z","trip_short_name":"TLK 403","direction_id":0,"version":"","countries":"CZ, PL","is_active":"Y","irregularities":"","service_id":"2026/06/26-2026/08/30: Daily","classes":"","connections":"","catering":"","plugs":"","wheelchair_accessible":"","bikes_allowed":"","car_transport":"","duration":"","distance":"","emissions_co2e":"","co2_per_km":"","via":"","":"","Merged Doc ID - ONTD_Chatbase_Export":"","Merged Doc URL - ONTD_Chatbase_Export":"","Link to merged Doc - ONTD_Chatbase_Export":"","Document Merge Status - ONTD_Chatbase_Export":""},"PKP/ČD TLK 402":{"route_id":266,"agency_id":"PKP/ČD","trip_id":"PKP/ČD TLK 402","trip_origin":"Łeba","origin_departure_time":"1899-12-30T19:11:00.000Z","trip_headsign":"Bohumín","destination_arrival_time":"1899-12-30T06:54:00.000Z","trip_short_name":"TLK 402","direction_id":1,"version":"","countries":"CZ, PL","is_active":"Y","irregularities":"","service_id":"2026/06/26-2026/08/30: Daily","classes":"","connections":"","catering":"","plugs":"","wheelchair_accessible":"","bikes_allowed":"","car_transport":"","duration":"","distance":"","emissions_co2e":"","co2_per_km":"","via":"","":"","Merged Doc ID - ONTD_Chatbase_Export":"","Merged Doc URL - ONTD_Chatbase_Export":"","Link to merged Doc - ONTD_Chatbase_Export":"","Document Merge Status - ONTD_Chatbase_Export":""},"RJ 1038":{"route_id":261,"agency_id":"RJ","trip_id":"RJ 1038","trip_origin":"Przemyśl Gł.","origin_departure_time":"1899-12-30T22:12:00.000Z","trip_headsign":"Praha hl.n.","destination_arrival_time":"1899-12-30T08:56:00.000Z","trip_short_name":"1038","direction_id":0,"version":"","countries":"PL, CZ","is_active":"Y","irregularities":"","service_id":"Daily","classes":"seat, couchette, sleeper","connections":"Lviv, Kyiv, Zaporizhzhia","catering":"","plugs":"","wheelchair_accessible":"","bikes_allowed":"","car_transport":2,"duration":"1899-12-30T10:44:00.000Z","distance":740,"emissions_co2e":20.6,"co2_per_km":27.837837837837842,"via":"Kraków Gł. - Olomouc hl.n.","":"#N/A","Merged Doc ID - ONTD_Chatbase_Export":"1GWLuutv4VN3px7uay2iCJEiNza9dApi5k5JUPCHid14","Merged Doc URL - ONTD_Chatbase_Export":"https://docs.google.com/document/d/1GWLuutv4VN3px7uay2iCJEiNza9dApi5k5JUPCHid14/edit?usp=drivesdk","Link to merged Doc - ONTD_Chatbase_Export":"ONTD_Chatbase_export_05/02/2025_May 2 2025 8:03 PM","Document Merge Status - ONTD_Chatbase_Export":"Data merged and appended successfully; Manually run by jme@wegewerk.com; Timestamp: May 2 2025 4:08 PM"},"RJ 1039":{"route_id":261,"agency_id":"RJ","trip_id":"RJ 1039","trip_origin":"Praha hl.n.","origin_departure_time":"1899-12-30T20:56:00.000Z","trip_headsign":"Przemyśl Gł.","destination_arrival_time":"1899-12-30T07:33:00.000Z","trip_short_name":"1039","direction_id":1,"version":"","countries":"PL, CZ","is_active":"Y","irregularities":"","service_id":"Daily","classes":"seat, couchette, sleeper","connections":"Lviv, Kyiv, Zaporizhzhia","catering":"","plugs":"","wheelchair_accessible":"","bikes_allowed":"","car_transport":2,"duration":"1899-12-30T10:37:00.000Z","distance":740,"emissions_co2e":20.6,"co2_per_km":27.837837837837842,"via":"Pardubice hl.n. - Olomouc hl.n. - Kraków Gł.","":"#N/A","Merged Doc ID - ONTD_Chatbase_Export":"1GWLuutv4VN3px7uay2iCJEiNza9dApi5k5JUPCHid14","Merged Doc URL - ONTD_Chatbase_Export":"https://docs.google.com/document/d/1GWLuutv4VN3px7uay2iCJEiNza9dApi5k5JUPCHid14/edit?usp=drivesdk","Link to merged Doc - ONTD_Chatbase_Export":"ONTD_Chatbase_export_05/02/2025_May 2 2025 8:03 PM","Document Merge Status - ONTD_Chatbase_Export":"Data merged and appended successfully; Manually run by jme@wegewerk.com; Timestamp: May 2 2025 4:08 PM"},"SJ Nattåg 91":{"route_id":81,"agency_id":"SJ","trip_id":"SJ Nattåg 91","trip_origin":"Luleå C","origin_departure_time":"1899-12-30T17:00:00.000Z","trip_headsign":"Stockholm C","destination_arrival_time":"1899-12-30T06:35:00.000Z","trip_short_name":"Nattåg 91","direction_id":0,"version":"","countries":"SE","is_active":"Y","irregularities":"","service_id":"Daily","classes":"seat, couchette, sleeper","connections":"","catering":4,"plugs":"","wheelchair_accessible":"","bikes_allowed":"","car_transport":2,"duration":"1899-12-30T13:35:00.000Z","distance":1052,"emissions_co2e":1.1,"co2_per_km":1.0456273764258557,"via":"Boden C - Umeå C - Örnsköldsvik C - Härnösand - Sundsvall C - Gävle C - Uppsala C - Arlanda","":"#N/A","Merged Doc ID - ONTD_Chatbase_Export":"1GWLuutv4VN3px7uay2iCJEiNza9dApi5k5JUPCHid14","Merged Doc URL - ONTD_Chatbase_Export":"https://docs.google.com/document/d/1GWLuutv4VN3px7uay2iCJEiNza9dApi5k5JUPCHid14/edit?usp=drivesdk","Link to merged Doc - ONTD_Chatbase_Export":"ONTD_Chatbase_export_05/02/2025_May 2 2025 8:03 PM","Document Merge Status - ONTD_Chatbase_Export":"Data merged and appended successfully; Manually run by jme@wegewerk.com; Timestamp: May 2 2025 4:08 PM"},"SJ Nattåg 92":{"route_id":81,"agency_id":"SJ","trip_id":"SJ Nattåg 92","trip_origin":"Stockholm C","origin_departure_time":"1899-12-30T21:55:00.000Z","trip_headsign":"Luleå C","destination_arrival_time":"1899-12-30T11:53:00.000Z","trip_short_name":"Nattåg 92","direction_id":1,"version":"","countries":"SE","is_active":"Y","irregularities":"","service_id":"Daily","classes":"seat, couchette, sleeper","connections":"","catering":4,"plugs":"","wheelchair_accessible":"","bikes_allowed":"","car_transport":2,"duration":"1899-12-30T13:58:00.000Z","distance":1052,"emissions_co2e":1.1,"co2_per_km":1.0456273764258557,"via":"Arlanda - Uppsala C - Gävle C - Örnsköldsvik C - Umeå C - Boden C","":"#N/A","Merged Doc ID - ONTD_Chatbase_Export":"1GWLuutv4VN3px7uay2iCJEiNza9dApi5k5JUPCHid14","Merged Doc URL - ONTD_Chatbase_Export":"https://docs.google.com/document/d/1GWLuutv4VN3px7uay2iCJEiNza9dApi5k5JUPCHid14/edit?usp=drivesdk","Link to merged Doc - ONTD_Chatbase_Export":"ONTD_Chatbase_export_05/02/2025_May 2 2025 8:03 PM","Document Merge Status - ONTD_Chatbase_Export":"Data merged and appended successfully; Manually run by jme@wegewerk.com; Timestamp: May 2 2025 4:08 PM"},"SJ Nattåg 93 (L)":{"route_id":68,"agency_id":"SJ","trip_id":"SJ Nattåg 93 (L)","trip_origin":"Luleå C","origin_departure_time":"1899-12-30T21:10:00.000Z","trip_headsign":"Stockholm C","destination_arrival_time":"1899-12-30T10:09:00.000Z","trip_short_name":"Nattåg 93 (L)","direction_id":0,"version":"","countries":"SE","is_active":"Y","irregularities":"","service_id":"Daily","classes":"seat, couchette, sleeper","connections":"bistro between Lulea - Boden","catering":3,"plugs":"","wheelchair_accessible":"","bikes_allowed":"","car_transport":2,"duration":"1899-12-30T12:59:00.000Z","distance":1052,"emissions_co2e":1.1,"co2_per_km":1.0456273764258557,"via":"Boden C - Umeå C - Örnsköldsvik C - Sundsvall C - Gävle C - Uppsala C - Arlanda","":"#N/A","Merged Doc ID - ONTD_Chatbase_Export":"1GWLuutv4VN3px7uay2iCJEiNza9dApi5k5JUPCHid14","Merged Doc URL - ONTD_Chatbase_Export":"https://docs.google.com/document/d/1GWLuutv4VN3px7uay2iCJEiNza9dApi5k5JUPCHid14/edit?usp=drivesdk","Link to merged Doc - ONTD_Chatbase_Export":"ONTD_Chatbase_export_05/02/2025_May 2 2025 8:03 PM","Document Merge Status - ONTD_Chatbase_Export":"Data merged and appended successfully; Manually run by jme@wegewerk.com; Timestamp: May 2 2025 4:08 PM"},"SJ Nattåg 94 (L)":{"route_id":68,"agency_id":"SJ","trip_id":"SJ Nattåg 94 (L)","trip_origin":"Stockholm C","origin_departure_time":"1899-12-30T18:08:00.000Z","trip_headsign":"Luleå C","destination_arrival_time":"1899-12-30T06:44:00.000Z","trip_short_name":"Nattåg 94 (L)","direction_id":1,"version":"","countries":"SE","is_active":"Y","irregularities":"","service_id":"Daily","classes":"seat, couchette, sleeper","connections":"bistro between Boden - Lulea","catering":3,"plugs":"","wheelchair_accessible":"","bikes_allowed":"","car_transport":2,"duration":"1899-12-30T12:36:00.000Z","distance":1052,"emissions_co2e":1.1,"co2_per_km":1.0456273764258557,"via":"Arlanda - Uppsala C - Gävle C - Sundsvall C - Härnösand - Örnsköldsvik C - Boden C","":"#N/A","Merged Doc ID - ONTD_Chatbase_Export":"1GWLuutv4VN3px7uay2iCJEiNza9dApi5k5JUPCHid14","Merged Doc URL - ONTD_Chatbase_Export":"https://docs.google.com/document/d/1GWLuutv4VN3px7uay2iCJEiNza9dApi5k5JUPCHid14/edit?usp=drivesdk","Link to merged Doc - ONTD_Chatbase_Export":"ONTD_Chatbase_export_05/02/2025_May 2 2025 8:03 PM","Document Merge Status - ONTD_Chatbase_Export":"Data merged and appended successfully; Manually run by jme@wegewerk.com; Timestamp: May 2 2025 4:08 PM"},"SJ Nattåg 93 (N)":{"route_id":66,"agency_id":"SJ","trip_id":"SJ Nattåg 93 (N)","trip_origin":"Narvik","origin_departure_time":"1899-12-30T15:11:00.000Z","trip_headsign":"Stockholm C","destination_arrival_time":"1899-12-30T10:09:00.000Z","trip_short_name":"Nattåg 93 (N)","direction_id":0,"version":"","countries":"SE, NO","is_active":"Y","irregularities":"","service_id":"Daily","classes":"seat, couchette, sleeper","connections":"bistro between Narvik - Boden","catering":3,"plugs":"","wheelchair_accessible":"","bikes_allowed":"","car_transport":2,"duration":"1899-12-30T18:58:00.000Z","distance":1456,"emissions_co2e":1.4,"co2_per_km":0.9615384615384615,"via":"Kiruna / Giron - Gällivare C - Boden C - Umeå C - Sundsvall C - Gävle C - Uppsala C - Arlanda","":"#N/A","Merged Doc ID - ONTD_Chatbase_Export":"1GWLuutv4VN3px7uay2iCJEiNza9dApi5k5JUPCHid14","Merged Doc URL - ONTD_Chatbase_Export":"https://docs.google.com/document/d/1GWLuutv4VN3px7uay2iCJEiNza9dApi5k5JUPCHid14/edit?usp=drivesdk","Link to merged Doc - ONTD_Chatbase_Export":"ONTD_Chatbase_export_05/02/2025_May 2 2025 8:03 PM","Document Merge Status - ONTD_Chatbase_Export":"Data merged and appended successfully; Manually run by jme@wegewerk.com; Timestamp: May 2 2025 4:08 PM"},"SJ Nattåg 94 (N)":{"route_id":66,"agency_id":"SJ","trip_id":"SJ Nattåg 94 (N)","trip_origin":"Stockholm C","origin_departure_time":"1899-12-30T18:08:00.000Z","trip_headsign":"Narvik","destination_arrival_time":"1899-12-30T12:40:00.000Z","trip_short_name":"Nattåg 94 (N)","direction_id":1,"version":"","countries":"SE, NO","is_active":"Y","irregularities":"","service_id":"Daily","classes":"seat, couchette, sleeper","connections":"bistro between Boden - Narvik","catering":3,"plugs":"","wheelchair_accessible":"","bikes_allowed":"","car_transport":2,"duration":"1899-12-30T18:32:00.000Z","distance":1456,"emissions_co2e":1.4,"co2_per_km":0.9615384615384615,"via":"Arlanda - Uppsala C - Gävle C - Sundsvall C - Härnösand - Örnsköldsvik C - Boden C - Gällivare C - Kiruna / Giron","":"#N/A","Merged Doc ID - ONTD_Chatbase_Export":"1GWLuutv4VN3px7uay2iCJEiNza9dApi5k5JUPCHid14","Merged Doc URL - ONTD_Chatbase_Export":"https://docs.google.com/document/d/1GWLuutv4VN3px7uay2iCJEiNza9dApi5k5JUPCHid14/edit?usp=drivesdk","Link to merged Doc - ONTD_Chatbase_Export":"ONTD_Chatbase_export_05/02/2025_May 2 2025 8:03 PM","Document Merge Status - ONTD_Chatbase_Export":"Data merged and appended successfully; Manually run by jme@wegewerk.com; Timestamp: May 2 2025 4:08 PM"},"UEX 1858":{"route_id":255,"agency_id":"UEX","trip_id":"UEX 1858","trip_origin":"Lörrach Hbf","origin_departure_time":"1899-12-30T20:36:00.000Z","trip_headsign":"Hamburg Altona","destination_arrival_time":"1899-12-30T07:35:00.000Z","trip_short_name":"1858","direction_id":0,"version":"","countries":"DE","is_active":"Y","irregularities":"Reportedly frequent cancellations and poor maintenance","service_id":"0-2 days/week (May-Oct)","classes":"couchette, sleeper","connections":"","catering":2,"plugs":1,"wheelchair_accessible":2,"bikes_allowed":1,"car_transport":1,"duration":"1899-12-30T10:59:00.000Z","distance":847,"emissions_co2e":"","co2_per_km":"","via":"Freiburg (Breisgau) Hbf - Karlsruhe Hbf - Hannover Hbf - Lüneburg - Hamburg Hbf","":"#N/A","Merged Doc ID - ONTD_Chatbase_Export":"1GWLuutv4VN3px7uay2iCJEiNza9dApi5k5JUPCHid14","Merged Doc URL - ONTD_Chatbase_Export":"https://docs.google.com/document/d/1GWLuutv4VN3px7uay2iCJEiNza9dApi5k5JUPCHid14/edit?usp=drivesdk","Link to merged Doc - ONTD_Chatbase_Export":"ONTD_Chatbase_export_05/02/2025_May 2 2025 8:03 PM","Document Merge Status - ONTD_Chatbase_Export":"Data merged and appended successfully; Manually run by jme@wegewerk.com; Timestamp: May 2 2025 4:08 PM"},"UEX 1859":{"route_id":255,"agency_id":"UEX","trip_id":"UEX 1859","trip_origin":"Hamburg Altona","origin_departure_time":"1899-12-30T21:32:00.000Z","trip_headsign":"Lörrach Hbf","destination_arrival_time":"1899-12-30T08:05:00.000Z","trip_short_name":"1859","direction_id":1,"version":"","countries":"DE","is_active":"Y","irregularities":"Reportedly frequent cancellations and poor maintenance","service_id":"0-2 days/week (May-Oct)","classes":"couchette, sleeper","connections":"","catering":2,"plugs":1,"wheelchair_accessible":2,"bikes_allowed":1,"car_transport":1,"duration":"1899-12-30T10:33:00.000Z","distance":847,"emissions_co2e":"","co2_per_km":"","via":"Hamburg Hbf - Hannover Hbf - Karlsruhe Hbf - Freiburg (Breisgau) Hbf","":"#N/A","Merged Doc ID - ONTD_Chatbase_Export":"1GWLuutv4VN3px7uay2iCJEiNza9dApi5k5JUPCHid14","Merged Doc URL - ONTD_Chatbase_Export":"https://docs.google.com/document/d/1GWLuutv4VN3px7uay2iCJEiNza9dApi5k5JUPCHid14/edit?usp=drivesdk","Link to merged Doc - ONTD_Chatbase_Export":"ONTD_Chatbase_export_05/02/2025_May 2 2025 8:03 PM","Document Merge Status - ONTD_Chatbase_Export":"Data merged and appended successfully; Manually run by jme@wegewerk.com; Timestamp: May 2 2025 4:08 PM"},"UEX 332/1372":{"route_id":256,"agency_id":"UEX","trip_id":"UEX 332/1372","trip_origin":"Innsbruck Hbf","origin_departure_time":"1899-12-30T21:00:00.000Z","trip_headsign":"Düsseldorf Hbf","destination_arrival_time":"1899-12-30T07:45:00.000Z","trip_short_name":"332/1372","direction_id":0,"version":"","countries":"DE","is_active":"Y","irregularities":"Reportedly frequent cancellations and poor maintenance","service_id":"0-2 days/week (May-Oct)","classes":"couchette, sleeper","connections":"","catering":2,"plugs":1,"wheelchair_accessible":2,"bikes_allowed":1,"car_transport":1,"duration":"1899-12-30T10:45:00.000Z","distance":"","emissions_co2e":"","co2_per_km":"","via":"Jenbach - München Ost - Augsburg Hbf - Gießen - Siegen - Siegburg (Bonn) - Köln Messe/Deutz","":"#N/A","Merged Doc ID - ONTD_Chatbase_Export":"1GWLuutv4VN3px7uay2iCJEiNza9dApi5k5JUPCHid14","Merged Doc URL - ONTD_Chatbase_Export":"https://docs.google.com/document/d/1GWLuutv4VN3px7uay2iCJEiNza9dApi5k5JUPCHid14/edit?usp=drivesdk","Link to merged Doc - ONTD_Chatbase_Export":"ONTD_Chatbase_export_05/02/2025_May 2 2025 8:03 PM","Document Merge Status - ONTD_Chatbase_Export":"Data merged and appended successfully; Manually run by jme@wegewerk.com; Timestamp: May 2 2025 4:08 PM"},"UEX 333/1373":{"route_id":256,"agency_id":"UEX","trip_id":"UEX 333/1373","trip_origin":"Düsseldorf Hbf","origin_departure_time":"1899-12-30T20:43:00.000Z","trip_headsign":"Innsbruck Hbf","destination_arrival_time":"1899-12-30T08:23:00.000Z","trip_short_name":"333/1373","direction_id":1,"version":"","countries":"DE","is_active":"Y","irregularities":"Reportedly frequent cancellations and poor maintenance","service_id":"0-2 days/week (May-Oct)","classes":"couchette, sleeper","connections":"","catering":2,"plugs":1,"wheelchair_accessible":2,"bikes_allowed":1,"car_transport":1,"duration":"1899-12-30T11:40:00.000Z","distance":"","emissions_co2e":"","co2_per_km":"","via":"Köln Messe/Deutz - Siegburg/Bonn - Siegen - Aschaffenburg Hbf - Augsburg Hbf - München Ost - Jenbach","":"#N/A","Merged Doc ID - ONTD_Chatbase_Export":"1GWLuutv4VN3px7uay2iCJEiNza9dApi5k5JUPCHid14","Merged Doc URL - ONTD_Chatbase_Export":"https://docs.google.com/document/d/1GWLuutv4VN3px7uay2iCJEiNza9dApi5k5JUPCHid14/edit?usp=drivesdk","Link to merged Doc - ONTD_Chatbase_Export":"ONTD_Chatbase_export_05/02/2025_May 2 2025 8:03 PM","Document Merge Status - ONTD_Chatbase_Export":"Data merged and appended successfully; Manually run by jme@wegewerk.com; Timestamp: May 2 2025 4:08 PM"},"UEX 334/1374":{"route_id":257,"agency_id":"UEX","trip_id":"UEX 334/1374","trip_origin":"Villach Hbf","origin_departure_time":"1899-12-30T19:06:00.000Z","trip_headsign":"Düsseldorf Hbf","destination_arrival_time":"1899-12-30T08:39:00.000Z","trip_short_name":"334/1374","direction_id":0,"version":"","countries":"DE","is_active":"Y","irregularities":"Reportedly frequent cancellations and poor maintenance","service_id":"0-2 days/week (May-Oct)","classes":"couchette, sleeper","connections":"","catering":2,"plugs":1,"wheelchair_accessible":2,"bikes_allowed":1,"car_transport":1,"duration":"1899-12-30T13:33:00.000Z","distance":"","emissions_co2e":"","co2_per_km":"","via":"Salzburg Hbf - München Ost - Aschaffenburg Hbf - Gießen - Siegen Hbf - Siegburg/Bonn - Köln Messe/Deutz","":"#N/A","Merged Doc ID - ONTD_Chatbase_Export":"1GWLuutv4VN3px7uay2iCJEiNza9dApi5k5JUPCHid14","Merged Doc URL - ONTD_Chatbase_Export":"https://docs.google.com/document/d/1GWLuutv4VN3px7uay2iCJEiNza9dApi5k5JUPCHid14/edit?usp=drivesdk","Link to merged Doc - ONTD_Chatbase_Export":"ONTD_Chatbase_export_05/02/2025_May 2 2025 8:03 PM","Document Merge Status - ONTD_Chatbase_Export":"Data merged and appended successfully; Manually run by jme@wegewerk.com; Timestamp: May 2 2025 4:08 PM"},"UEX 335/1375":{"route_id":257,"agency_id":"UEX","trip_id":"UEX 335/1375","trip_origin":"Düsseldorf Hbf","origin_departure_time":"1899-12-30T19:53:00.000Z","trip_headsign":"Villach Hbf","destination_arrival_time":"1899-12-30T08:38:00.000Z","trip_short_name":"335/1375","direction_id":1,"version":"","countries":"DE","is_active":"Y","irregularities":"Reportedly frequent cancellations and poor maintenance","service_id":"0-2 days/week (May-Oct)","classes":"couchette, sleeper","connections":"","catering":2,"plugs":1,"wheelchair_accessible":2,"bikes_allowed":1,"car_transport":1,"duration":"1899-12-30T12:45:00.000Z","distance":"","emissions_co2e":"","co2_per_km":"","via":"Köln Messe/Deutz - Siegen Hbf - Aschaffenburg Hbf - München Ost - Salzburg Hbf","":"#N/A","Merged Doc ID - ONTD_Chatbase_Export":"1GWLuutv4VN3px7uay2iCJEiNza9dApi5k5JUPCHid14","Merged Doc URL - ONTD_Chatbase_Export":"https://docs.google.com/document/d/1GWLuutv4VN3px7uay2iCJEiNza9dApi5k5JUPCHid14/edit?usp=drivesdk","Link to merged Doc - ONTD_Chatbase_Export":"ONTD_Chatbase_export_05/02/2025_May 2 2025 8:03 PM","Document Merge Status - ONTD_Chatbase_Export":"Data merged and appended successfully; Manually run by jme@wegewerk.com; Timestamp: May 2 2025 4:08 PM"},"UZ 009":{"route_id":183,"agency_id":"UZ","trip_id":"UZ 009","trip_origin":"Kyiv Pasazhyrskyi","origin_departure_time":"1899-12-30T09:43:00.000Z","trip_headsign":"Budapest Keleti","destination_arrival_time":"1899-12-30T06:00:00.000Z","trip_short_name":"009","direction_id":0,"version":"","countries":"HU, UA","is_active":"Y","irregularities":"","service_id":"2026: Daily","classes":"sleeper","connections":"","catering":"","plugs":"","wheelchair_accessible":"","bikes_allowed":"","car_transport":2,"duration":"1899-12-30T20:17:00.000Z","distance":1171,"emissions_co2e":22.5,"co2_per_km":19.214346712211785,"via":"Lviv - Mukacheve - Chop - Nyíregyháza - Szolnok","":"#N/A","Merged Doc ID - ONTD_Chatbase_Export":"1GWLuutv4VN3px7uay2iCJEiNza9dApi5k5JUPCHid14","Merged Doc URL - ONTD_Chatbase_Export":"https://docs.google.com/document/d/1GWLuutv4VN3px7uay2iCJEiNza9dApi5k5JUPCHid14/edit?usp=drivesdk","Link to merged Doc - ONTD_Chatbase_Export":"ONTD_Chatbase_export_05/02/2025_May 2 2025 8:03 PM","Document Merge Status - ONTD_Chatbase_Export":"Data merged and appended successfully; Manually run by jme@wegewerk.com; Timestamp: May 2 2025 4:08 PM"},"UZ 010":{"route_id":183,"agency_id":"UZ","trip_id":"UZ 010","trip_origin":"Budapest Keleti","origin_departure_time":"1899-12-30T22:40:00.000Z","trip_headsign":"Kyiv Pasazhyrskyi","destination_arrival_time":"1899-12-30T19:54:00.000Z","trip_short_name":"010","direction_id":1,"version":"","countries":"HU, UA","is_active":"Y","irregularities":"","service_id":"2026: Daily","classes":"sleeper","connections":"","catering":"","plugs":"","wheelchair_accessible":"","bikes_allowed":"","car_transport":2,"duration":"1899-12-30T21:14:00.000Z","distance":1171,"emissions_co2e":22.5,"co2_per_km":19.214346712211785,"via":"Szolnok - Debrecen - Chop - Mukacheve - Lviv","":"#N/A","Merged Doc ID - ONTD_Chatbase_Export":"1GWLuutv4VN3px7uay2iCJEiNza9dApi5k5JUPCHid14","Merged Doc URL - ONTD_Chatbase_Export":"https://docs.google.com/document/d/1GWLuutv4VN3px7uay2iCJEiNza9dApi5k5JUPCHid14/edit?usp=drivesdk","Link to merged Doc - ONTD_Chatbase_Export":"ONTD_Chatbase_export_05/02/2025_May 2 2025 8:03 PM","Document Merge Status - ONTD_Chatbase_Export":"Data merged and appended successfully; Manually run by jme@wegewerk.com; Timestamp: May 2 2025 4:08 PM"},"UZ 067":{"route_id":181,"agency_id":"UZ","trip_id":"UZ 067","trip_origin":"Kyiv Pasazhyrskyi","origin_departure_time":"1899-12-30T19:06:00.000Z","trip_headsign":"Warszawa Zachodnia","destination_arrival_time":"1899-12-30T09:53:00.000Z","trip_short_name":"067","direction_id":0,"version":"","countries":"PL, UA","is_active":"Y","irregularities":"Quickly booked out","service_id":"2026: Daily","classes":"sleeper","connections":"","catering":"","plugs":"","wheelchair_accessible":"","bikes_allowed":"","car_transport":2,"duration":"1899-12-30T14:47:00.000Z","distance":867,"emissions_co2e":15.55061425061425,"co2_per_km":17.936117936117935,"via":"Kovel - Chelm - Lublin - Warszawa Wschodnia - Warszawa Centralna","":"#N/A","Merged Doc ID - ONTD_Chatbase_Export":"1GWLuutv4VN3px7uay2iCJEiNza9dApi5k5JUPCHid14","Merged Doc URL - ONTD_Chatbase_Export":"https://docs.google.com/document/d/1GWLuutv4VN3px7uay2iCJEiNza9dApi5k5JUPCHid14/edit?usp=drivesdk","Link to merged Doc - ONTD_Chatbase_Export":"ONTD_Chatbase_export_05/02/2025_May 2 2025 8:03 PM","Document Merge Status - ONTD_Chatbase_Export":"Data merged and appended successfully; Manually run by jme@wegewerk.com; Timestamp: May 2 2025 4:08 PM"},"UZ 068":{"route_id":181,"agency_id":"UZ","trip_id":"UZ 068","trip_origin":"Warszawa Zachodnia","origin_departure_time":"1899-12-30T18:15:00.000Z","trip_headsign":"Kyiv Pasazhyrskyi","destination_arrival_time":"1899-12-30T10:45:00.000Z","trip_short_name":"068","direction_id":1,"version":"","countries":"PL, UA","is_active":"Y","irregularities":"Quickly booked out","service_id":"2026: Daily","classes":"sleeper","connections":"","catering":"","plugs":"","wheelchair_accessible":"","bikes_allowed":"","car_transport":2,"duration":"1899-12-30T16:30:00.000Z","distance":867,"emissions_co2e":15.55061425061425,"co2_per_km":17.936117936117935,"via":"Warszawa Centralna - Warszawa Wschodnia - Lublin - Chelm - Kovel","":"#N/A","Merged Doc ID - ONTD_Chatbase_Export":"1GWLuutv4VN3px7uay2iCJEiNza9dApi5k5JUPCHid14","Merged Doc URL - ONTD_Chatbase_Export":"https://docs.google.com/document/d/1GWLuutv4VN3px7uay2iCJEiNza9dApi5k5JUPCHid14/edit?usp=drivesdk","Link to merged Doc - ONTD_Chatbase_Export":"ONTD_Chatbase_export_05/02/2025_May 2 2025 8:03 PM","Document Merge Status - ONTD_Chatbase_Export":"Data merged and appended successfully; Manually run by jme@wegewerk.com; Timestamp: May 2 2025 4:08 PM"},"":{"route_id":"","agency_id":"#N/A","trip_id":"","trip_origin":"","origin_departure_time":"","trip_headsign":"","destination_arrival_time":"","trip_short_name":"","direction_id":"","version":"","countries":"","is_active":"","irregularities":"","service_id":"","classes":"","connections":"","catering":"","plugs":"","wheelchair_accessible":"","bikes_allowed":"","car_transport":"","duration":"","distance":"","emissions_co2e":"","co2_per_km":"","via":"","":"","Merged Doc ID - ONTD_Chatbase_Export":"","Merged Doc URL - ONTD_Chatbase_Export":"","Link to merged Doc - ONTD_Chatbase_Export":"","Document Merge Status - ONTD_Chatbase_Export":""},"UZ 099":{"route_id":174,"agency_id":"UZ","trip_id":"UZ 099","trip_origin":"Kyiv Pasazhyrskyi","origin_departure_time":"1899-12-30T06:30:00.000Z","trip_headsign":"București Nord","destination_arrival_time":"1899-12-30T06:47:00.000Z","trip_short_name":"099","direction_id":0,"version":"","countries":"UA, MD, RO","is_active":"Y","irregularities":"","service_id":"2025: Daily","classes":"couchette","connections":"","catering":"","plugs":"","wheelchair_accessible":"","bikes_allowed":"","car_transport":2,"duration":"1899-12-30T23:17:00.000Z","distance":1036,"emissions_co2e":16.6,"co2_per_km":16.023166023166024,"via":"Vinnytsia - Zhmerynka - Nicolina - Iași - Mizil - Ploiești Sud","":"#N/A","Merged Doc ID - ONTD_Chatbase_Export":"","Merged Doc URL - ONTD_Chatbase_Export":"","Link to merged Doc - ONTD_Chatbase_Export":"","Document Merge Status - ONTD_Chatbase_Export":""},"UZ 100":{"route_id":174,"agency_id":"UZ","trip_id":"UZ 100","trip_origin":"București Nord","origin_departure_time":"1899-12-30T19:10:00.000Z","trip_headsign":"Kyiv Pasazhyrskyi","destination_arrival_time":"1899-12-30T19:37:00.000Z","trip_short_name":"100","direction_id":1,"version":"","countries":"UA, MD, RO","is_active":"Y","irregularities":"","service_id":"2025: Daily","classes":"couchette","connections":"","catering":"","plugs":"","wheelchair_accessible":"","bikes_allowed":"","car_transport":2,"duration":"1899-12-30T23:27:00.000Z","distance":1036,"emissions_co2e":16.6,"co2_per_km":16.023166023166024,"via":"Ploiești Sud - Mizil - Buzău - Focșani - Adjud - Bacău - Roman - Zhmerynka - Vinnytsia","":"#N/A","Merged Doc ID - ONTD_Chatbase_Export":"","Merged Doc URL - ONTD_Chatbase_Export":"","Link to merged Doc - ONTD_Chatbase_Export":"","Document Merge Status - ONTD_Chatbase_Export":""}}